Workbook

Sheet Resumen
A1: Resumen de reliquias
A2: Se actualiza solo al cambiar los desplegables de Estado.
A4: Clase | B4: Total | C4: Existentes | D4: Nuevas | E4: Pendiente | F4: Aprobada | G4: Ajustar | H4: Rechazada
A5: Neutral | B5: =COUNTIF(Reliquias!$C$5:$C$159,A5) -> 84 | C5: =COUNTIFS(Reliquias!$C$5:$C$159,A5,Reliquias!$H$5:$H$159,"Existente") -> 25 | D5: =B5-C5 -> 59 | E5: =COUNTIFS(Reliquias!$C$5:$C$159,$A5,Reliquias!$I$5:$I$159,"Pendiente") -> 0 | F5: =COUNTIFS(Reliquias!$C$5:$C$159,$A5,Reliquias!$I$5:$I$159,"Aprobada") -> 84 | G5: =COUNTIFS(Reliquias!$C$5:$C$159,$A5,Reliquias!$I$5:$I$159,"Ajustar") -> 0 | H5: =COUNTIFS(Reliquias!$C$5:$C$159,$A5,Reliquias!$I$5:$I$159,"Rechazada") -> 0
A6: Guerrera | B6: =COUNTIF(Reliquias!$C$5:$C$159,A6) -> 23 | C6: =COUNTIFS(Reliquias!$C$5:$C$159,A6,Reliquias!$H$5:$H$159,"Existente") -> 5 | D6: =B6-C6 -> 18 | E6: =COUNTIFS(Reliquias!$C$5:$C$159,$A6,Reliquias!$I$5:$I$159,"Pendiente") -> 0 | F6: =COUNTIFS(Reliquias!$C$5:$C$159,$A6,Reliquias!$I$5:$I$159,"Aprobada") -> 23 | G6: =COUNTIFS(Reliquias!$C$5:$C$159,$A6,Reliquias!$I$5:$I$159,"Ajustar") -> 0 | H6: =COUNTIFS(Reliquias!$C$5:$C$159,$A6,Reliquias!$I$5:$I$159,"Rechazada") -> 0
A7: Mago | B7: =COUNTIF(Reliquias!$C$5:$C$159,A7) -> 18 | C7: =COUNTIFS(Reliquias!$C$5:$C$159,A7,Reliquias!$H$5:$H$159,"Existente") -> 0 | D7: =B7-C7 -> 18 | E7: =COUNTIFS(Reliquias!$C$5:$C$159,$A7,Reliquias!$I$5:$I$159,"Pendiente") -> 0 | F7: =COUNTIFS(Reliquias!$C$5:$C$159,$A7,Reliquias!$I$5:$I$159,"Aprobada") -> 18 | G7: =COUNTIFS(Reliquias!$C$5:$C$159,$A7,Reliquias!$I$5:$I$159,"Ajustar") -> 0 | H7: =COUNTIFS(Reliquias!$C$5:$C$159,$A7,Reliquias!$I$5:$I$159,"Rechazada") -> 0
A8: Pícara | B8: =COUNTIF(Reliquias!$C$5:$C$159,A8) -> 30 | C8: =COUNTIFS(Reliquias!$C$5:$C$159,A8,Reliquias!$H$5:$H$159,"Existente") -> 12 | D8: =B8-C8 -> 18 | E8: =COUNTIFS(Reliquias!$C$5:$C$159,$A8,Reliquias!$I$5:$I$159,"Pendiente") -> 0 | F8: =COUNTIFS(Reliquias!$C$5:$C$159,$A8,Reliquias!$I$5:$I$159,"Aprobada") -> 30 | G8: =COUNTIFS(Reliquias!$C$5:$C$159,$A8,Reliquias!$I$5:$I$159,"Ajustar") -> 0 | H8: =COUNTIFS(Reliquias!$C$5:$C$159,$A8,Reliquias!$I$5:$I$159,"Rechazada") -> 0
A9: Total | B9: =SUM(B5:B8) -> 155 | C9: =SUM(C5:C8) -> 42 | D9: =SUM(D5:D8) -> 113 | E9: =SUM(E5:E8) -> 0 | F9: =SUM(F5:F8) -> 155 | G9: =SUM(G5:G8) -> 0 | H9: =SUM(H5:H8) -> 0
A11: Por rareza (nuevas)
A12: Rareza | B12: Nuevas
A13: Común | B13: =COUNTIFS(Reliquias!$D$5:$D$159,A13,Reliquias!$H$5:$H$159,"<>Existente") -> 23
A14: Poco común | B14: =COUNTIFS(Reliquias!$D$5:$D$159,A14,Reliquias!$H$5:$H$159,"<>Existente") -> 28
A15: Rara | B15: =COUNTIFS(Reliquias!$D$5:$D$159,A15,Reliquias!$H$5:$H$159,"<>Existente") -> 32
A16: Épica | B16: =COUNTIFS(Reliquias!$D$5:$D$159,A16,Reliquias!$H$5:$H$159,"<>Existente") -> 19
A17: Legendaria | B17: =COUNTIFS(Reliquias!$D$5:$D$159,A17,Reliquias!$H$5:$H$159,"<>Existente") -> 11

Sheet Reliquias
A1: Reliquias de Last Wish
A2: Celdas amarillas para rellenar: Estado (desplegable) y Comentarios. Las 42 reliquias que ya están en el juego aparecen como Aprobadas solo para tener el registro. Columna «Efecto fuerte»: robar cartas, ganar maná, abaratar cartas y eliminar cartas son efectos muy poderosos; deben dar poco o tener una condición difícil (ver hoja «Reglas de equilibrio»).
A4: # | B4: Reliquia | C4: Clase | D4: Rareza | E4: Efecto | F4: Categoría | G4: Efecto fuerte | H4: Origen | I4: Estado | J4: Comentarios
A5: 1 | B5: Anillo de Oro | C5: Neutral | D5: Común | E5: +15 de oro extra por victoria de combate. | F5: — | H5: Existente | I5: Aprobada
A6: 2 | B6: Poción de Sangre | C6: Neutral | D6: Común | E6: Recupera 8 HP después de cada combate. | F6: — | H6: Existente | I6: Aprobada
A7: 3 | B7: Amuleto de Vitalidad | C7: Neutral | D7: Común | E7: +10 de HP máximo permanente. | F7: — | H7: Existente | I7: Aprobada
A8: 4 | B8: Máscara del Ladrón | C8: Neutral | D8: Común | E8: +25% de oro en los combates y la tienda es un 10% más barata. | F8: — | H8: Existente | I8: Aprobada
A9: 5 | B9: Cicatriz | C9: Neutral | D9: Común | E9: Empiezas cada combate con 1 de Fuerza. | F9: — | H9: Existente | I9: Aprobada
A10: 6 | B10: Brazal de Guerra | C10: Neutral | D10: Común | E10: Al empezar cada combate ganas 8 de escudo. | F10: — | H10: Existente | I10: Aprobada
A11: 7 | B11: Orbe de Fuego | C11: Neutral | D11: Poco común | E11: +2 de daño en todos los ataques. | F11: — | H11: Existente | I11: Aprobada
A12: 8 | B12: Corazón de Hierro | C12: Neutral | D12: Poco común | E12: +15 de HP máximo permanente. | F12: — | H12: Existente | I12: Aprobada
A13: 9 | B13: Moneda de la Suerte | C13: Neutral | D13: Poco común | E13: Si un efecto al azar golpea dos veces seguidas al mismo enemigo, ganas 1 de maná (una vez por turno). | F13: — | G13: Maná | H13: Existente | I13: Aprobada
A14: 10 | B14: Herradura de Plata | C14: Neutral | D14: Poco común | E14: +30 de suerte. | F14: — | H14: Existente | I14: Aprobada
A15: 11 | B15: Tótem Roto | C15: Neutral | D15: Rara | E15: +1 carta robada al inicio de cada turno. | F15: — | G15: Robo | H15: Existente | I15: Aprobada
A16: 12 | B16: Piedra de Energía | C16: Neutral | D16: Rara | E16: +1 carta robada al inicio de cada turno. | F16: — | G16: Robo | H16: Existente | I16: Aprobada
A17: 13 | B17: Guante de Seda | C17: Neutral | D17: Rara | E17: La tercera carta que juegas cada turno cuesta 0. | F17: — | G17: Maná | H17: Existente | I17: Aprobada
A18: 14 | B18: Botas Silenciosas | C18: Neutral | D18: Rara | E18: En el primer turno de cada combate robas 2 cartas extra. | F18: — | G18: Robo | H18: Existente | I18: Aprobada
A19: 15 | B19: Amuleto de Combate | C19: Neutral | D19: Épica | E19: +1 maná máximo al inicio del combate. | F19: — | G19: Maná | H19: Existente | I19: Aprobada
A20: 16 | B20: Hilo de Araña | C20: Neutral | D20: Épica | E20: Si terminas el turno sin cartas en la mano, ganas 6 de escudo. | F20: — | H20: Existente | I20: Aprobada
A21: 17 | B21: Llave Maestra | C21: Neutral | D21: Épica | E21: Las salas del tesoro te dejan elegir entre 2 reliquias. | F21: — | H21: Existente | I21: Aprobada
A22: 18 | B22: Interés Compuesto | C22: Neutral | D22: Épica | E22: Cada vez que ganas oro, ganas además un 10% de tu oro total. | F22: — | H22: Existente | I22: Aprobada
A23: 19 | B23: Escudo Espectral | C23: Neutral | D23: Legendaria | E23: Sobrevive una vez con 1 HP a un golpe fatal. | F23: — | H23: Existente | I23: Aprobada
A24: 20 | B24: Trébol de Siete Hojas | C24: Neutral | D24: Legendaria | E24: +100 de suerte: muchas más cartas y reliquias doradas y de mayor rareza. | F24: — | H24: Existente | I24: Aprobada
A25: 21 | B25: Panacea | C25: Neutral | D25: Legendaria | E25: Eres inmune a cualquier debuff de los enemigos. | F25: — | H25: Existente | I25: Aprobada
A26: 22 | B26: Fuente Eterna | C26: Neutral | D26: Legendaria | E26: Al inicio de cada turno ganas 1 de maná máximo. | F26: — | G26: Maná | H26: Existente | I26: Aprobada
A27: 23 | B27: Ankh | C27: Neutral | D27: Legendaria | E27: Al recibir un golpe fatal, revives con toda tu vida (una vez). | F27: — | H27: Existente | I27: Aprobada
A28: 24 | B28: Espejo Singular | C28: Neutral | D28: Legendaria | E28: Al obtenerla, elimina todas tus cartas repetidas: te quedas con una copia de cada carta. | F28: — | G28: Remover | H28: Existente | I28: Aprobada
A29: 25 | B29: Reloj Roto | C29: Neutral | D29: Legendaria | E29: Una vez por combate, al quedarte en 0 de maná con cartas en la mano, recuperas todo el maná. | F29: — | G29: Maná | H29: Existente | I29: Aprobada
A30: 26 | B30: Colmillo de Hierro | C30: Guerrera | D30: Poco común | E30: Tu primer ataque de cada turno te cura 2. | F30: — | H30: Existente | I30: Aprobada
A31: 27 | B31: Venda Empapada | C31: Guerrera | D31: Poco común | E31: La primera vez que pierdes vida en tu turno, robas 1 carta. | F31: — | G31: Robo | H31: Existente | I31: Aprobada
A32: 28 | B32: Copa de Sangre | C32: Guerrera | D32: Rara | E32: Todas tus curaciones en combate curan 2 más. | F32: — | H32: Existente | I32: Aprobada
A33: 29 | B33: Estandarte Desgarrado | C33: Guerrera | D33: Épica | E33: Cada 3 veces que activas Furia, ganas 1 de Fuerza. | F33: — | H33: Existente | I33: Aprobada
A34: 30 | B34: Corazón de Titán | C34: Guerrera | D34: Legendaria | E34: La curación que sobrepasa tu vida máxima te da el doble de escudo. | F34: — | H34: Existente | I34: Aprobada
A35: 31 | B35: Saco de Trapos | C35: Pícara | D35: Común | E35: Cada vez que activas un Despojo, ganas 2 de escudo. | F35: — | H35: Existente | I35: Aprobada
A36: 32 | B36: Bolsa de Dagas | C36: Pícara | D36: Común | E36: Al inicio de cada combate, mete 2 Dagas Ocultas en tu pila de robo. | F36: — | H36: Existente | I36: Aprobada
A37: 33 | B37: Broche de Evasión | C37: Pícara | D37: Poco común | E37: Cada vez que activas un Combo, ganas 1 de bloqueo. | F37: — | H37: Existente | I37: Aprobada
A38: 34 | B38: Cuchillo Arrojadizo | C38: Pícara | D38: Poco común | E38: Cada vez que activas un Combo, inflige 1 de daño a un enemigo al azar. | F38: — | H38: Existente | I38: Aprobada
A39: 35 | B39: Pañuelo del Duelista | C39: Pícara | D39: Poco común | E39: Cuando una carta activa su Combo, hace +2 de daño y da +2 de escudo. | F39: — | H39: Existente | I39: Aprobada
A40: 36 | B40: Garfio | C40: Pícara | D40: Poco común | E40: La primera vez que activas un Despojo cada turno, robas 1 carta. | F40: — | G40: Robo | H40: Existente | I40: Aprobada
A41: 37 | B41: Vaina Afilada | C41: Pícara | D41: Poco común | E41: Tus Dagas Ocultas hacen +2 de daño. | F41: — | H41: Existente | I41: Aprobada
A42: 38 | B42: Frasco de Veneno | C42: Pícara | D42: Poco común | E42: Tu primer ataque de cada turno aplica 1 de Veneno. | F42: — | H42: Existente | I42: Aprobada
A43: 39 | B43: Cinta Roja | C43: Pícara | D43: Rara | E43: En el primer turno de cada combate, tus Combos se activan sin jugar otra carta antes. | F43: — | H43: Existente | I43: Aprobada
A44: 40 | B44: Bolsillo Roto | C44: Pícara | D44: Rara | E44: Al inicio de cada turno, tras robar, descarta una carta al azar y roba 1. | F44: — | G44: Robo | H44: Existente | I44: Aprobada
A45: 41 | B45: Colmillo de Víbora | C45: Pícara | D45: Rara | E45: Cuando un enemigo muere envenenado, su Veneno pasa a otro enemigo al azar. | F45: — | H45: Existente | I45: Aprobada
A46: 42 | B46: Daga Partida | C46: Pícara | D46: Legendaria | E46: Tus efectos de Despojo se activan dos veces. | F46: — | H46: Existente | I46: Aprobada
A47: 43 | B47: Escalera | C47: Neutral | D47: Épica | E47: Si este turno juegas 3 cartas seguidas que cuesten 1 de maná más que la anterior (p. ej. 0-1-2), ganas +1 de Daño y +1 de Destreza para el resto del combate. | F47: Combate | H47: Idea del usuario | I47: Aprobada
A48: 44 | B48: Cartas de Diamante | C48: Neutral | D48: Legendaria | E48: Tus cartas doradas pasan a ser de Diamante: se lanzan 3 veces en lugar de 2. | F48: Mazo | H48: Idea del usuario | I48: Aprobada
A49: 45 | B49: Sello del Coleccionista | C49: Neutral | D49: Legendaria | E49: Ya no te salen cartas Comunes ni Poco comunes en sobres ni recompensas. | F49: Mazo | H49: Idea del usuario | I49: Aprobada | J49: Agrega una version para reliquias
A50: 46 | B50: Pieza Única | C50: Neutral | D50: Legendaria | E50: Si tu mazo no tiene cartas repetidas, la primera carta que juegas cada turno cuesta 1 menos. | F50: Combate | G50: Maná | H50: Idea del usuario | I50: Aprobada
A51: 47 | B51: Tijeras del Sastre | C51: Neutral | D51: Legendaria | E51: Al obtenerla, elimina 3 cartas de tu mazo a tu elección. | F51: Mazo | G51: Remover | H51: Idea del usuario | I51: Aprobada
A52: 48 | B52: Piedra de Afilar | C52: Neutral | D52: Común | E52: Tu primer ataque de cada combate hace +6 de daño. | F52: Combate | H52: Nueva | I52: Aprobada
A53: 49 | B53: Capa Raída | C53: Neutral | D53: Común | E53: Al final de tu turno, si no tienes escudo, ganas 3. | F53: Supervivencia | H53: Nueva | I53: Aprobada
A54: 50 | B54: Vela Votiva | C54: Neutral | D54: Común | E54: Al empezar cada combate, el enemigo con más vida recibe 1 de Débil. | F54: Combate | H54: Nueva | I54: Aprobada
A55: 51 | B55: Bandera Blanca | C55: Neutral | D55: Común | E55: El primer golpe que recibes en cada combate hace 4 menos de daño. | F55: Supervivencia | H55: Nueva | I55: Aprobada
A56: 52 | B56: Diente de León | C56: Neutral | D56: Común | E56: Cada vez que derrotas a un enemigo, te curas 3. | F56: Supervivencia | H56: Nueva | I56: Aprobada
A57: 53 | B57: Lámpara de Aceite | C57: Neutral | D57: Común | E57: En tu primer turno de cada combate, tus cartas de escudo dan +3. | F57: Supervivencia | H57: Nueva | I57: Aprobada
A58: 54 | B58: Fruta Silvestre | C58: Neutral | D58: Común | E58: Al obtenerla, +7 de vida máxima. | F58: Supervivencia | H58: Nueva | I58: Aprobada
A59: 55 | B59: Antídoto | C59: Neutral | D59: Común | E59: El Veneno que tienes baja 2 por turno en lugar de 1. | F59: Supervivencia | H59: Nueva | I59: Aprobada | J59: No me queda claro sería mejor que seas inmune
A60: 56 | B60: Bolsa Agujereada | C60: Neutral | D60: Común | E60: Ganas 5 de oro al terminar cada sala. | F60: Economía | H60: Nueva | I60: Aprobada
A61: 57 | B61: Cantimplora | C61: Neutral | D61: Común | E61: Si ganas un combate sin perder vida, +15 de oro. | F61: Economía | H61: Nueva | I61: Aprobada
A62: 58 | B62: Vale de Descuento | C62: Neutral | D62: Común | E62: La próxima tienda que visites te regala una carta (se gasta al usarlo). | F62: Economía | H62: Nueva | I62: Aprobada | J62: En lugar de carta que sea reliquia
A63: 59 | B63: Cuerno de Guerra | C63: Neutral | D63: Poco común | E63: En el turno 3 de cada combate, tus ataques hacen +4 de daño. | F63: Combate | H63: Nueva | I63: Aprobada
A64: 60 | B64: Saco de Arena | C64: Neutral | D64: Poco común | E64: Si terminas el turno habiendo jugado 3 cartas o más, ganas 4 de escudo. | F64: Supervivencia | H64: Nueva | I64: Aprobada
A65: 61 | B65: Ficha de Ajedrez | C65: Neutral | D65: Poco común | E65: Si en un turno juegas exactamente 2 cartas, ganas 5 de escudo. | F65: Supervivencia | H65: Nueva | I65: Aprobada
A66: 62 | B66: Pergamino Viejo | C66: Neutral | D66: Poco común | E66: La primera Habilidad de cada combate cuesta 0. | F66: Combate | G66: Maná | H66: Nueva | I66: Aprobada
A67: 63 | B67: Pila Ordenada | C67: Neutral | D67: Poco común | E67: Cada vez que barajas tu descarte en la pila de robo, ganas 4 de escudo. | F67: Supervivencia | H67: Nueva | I67: Aprobada
A68: 64 | B68: Vendas del Monje | C68: Neutral | D68: Poco común | E68: El primer debuff que recibes en cada combate no te afecta. | F68: Supervivencia | H68: Nueva | I68: Aprobada
A69: 65 | B69: Catalejo | C69: Neutral | D69: Poco común | E69: Puedes ver las 3 primeras cartas de tu pila de robo. | F69: Mazo | H69: Nueva | I69: Aprobada
A70: 66 | B70: Pata de Conejo | C70: Neutral | D70: Poco común | E70: +15 de suerte. | F70: Suerte | H70: Nueva | I70: Aprobada
A71: 67 | B71: Pico de Minero | C71: Neutral | D71: Poco común | E71: Las salas del tesoro dan además 25 de oro. | F71: Economía | H71: Nueva | I71: Aprobada
A72: 68 | B72: Hucha | C72: Neutral | D72: Poco común | E72: Al entrar en una tienda, ganas 1 de oro por cada 10 que tengas (máx. 15). | F72: Economía | H72: Nueva | I72: Aprobada
A73: 69 | B73: Calavera Sonriente | C73: Neutral | D73: Poco común | E73: Las élites dan +30 de oro. | F73: Economía | H73: Nueva | I73: Aprobada
A74: 70 | B74: Yunque Portátil | C74: Neutral | D74: Poco común | E74: Al obtenerla, mejora 1 carta al azar de tu mazo. | F74: Mazo | H74: Nueva | I74: Aprobada
A75: 71 | B75: Dado Cargado | C75: Neutral | D75: Poco común | E75: Una vez por sobre, puedes volver a tirar las cartas que ofrece. | F75: Mazo | H75: Nueva | I75: Aprobada
A76: 72 | B76: Corona de Espinas | C76: Neutral | D76: Rara | E76: Cada vez que un enemigo te golpea, recibe 2 de daño. | F76: Combate | H76: Nueva | I76: Aprobada
A77: 73 | B77: Amuleto de Escarcha | C77: Neutral | D77: Rara | E77: Al empezar cada combate, un enemigo normal al azar queda Congelado (pierde su primera acción). No afecta a jefes ni élites. | F77: Combate | H77: Nueva | I77: Aprobada
A78: 74 | B78: Lanza de Ruptura | C78: Neutral | D78: Rara | E78: Tus ataques contra enemigos con escudo hacen +3 de daño. | F78: Combate | H78: Nueva | I78: Aprobada
... A81: 77 | B81: Cuenco Vacío | C81: Neutral | D81: Rara | E81: Al final de tu turno, ganas 3 de escudo por cada maná que no gastaste. | F81: Supervivencia | H81: Nueva | I81: Aprobada
A82: 78 | B82: Reloj de Arena | C82: Neutral | D82: Rara | E82: Cada 4 turnos de combate, robas 1 carta extra. | F82: Combate | G82: Robo | H82: Nueva | I82: Aprobada
A83: 79 | B83: Ancla | C83: Neutral | D83: Rara | E83: Tu escudo del primer turno de cada combate no se pierde al empezar el segundo. | F83: Supervivencia | H83: Nueva | I83: Aprobada
A84: 80 | B84: Cartas Marcadas | C84: Neutral | D84: Rara | E84: Al empezar cada combate, eliges 1 carta de tu mazo para que esté en tu mano inicial (en lugar de una al azar). | F84: Mazo | H84: Nueva | I84: Aprobada
A85: 81 | B85: Medalla del Veterano | C85: Neutral | D85: Rara | E85: Cada vez que vences a una élite, +3 de vida máxima. | F85: Supervivencia | H85: Nueva | I85: Aprobada
A86: 82 | B86: Hoja de Laurel | C86: Neutral | D86: Rara | E86: Al vencer a un jefe, te curas toda la vida. | F86: Supervivencia | H86: Nueva | I86: Aprobada
A87: 83 | B87: Tarjeta de Socio | C87: Neutral | D87: Rara | E87: La primera compra en cada tienda cuesta la mitad. | F87: Economía | H87: Nueva | I87: Aprobada
A88: 84 | B88: Trofeo de Caza | C88: Neutral | D88: Rara | E88: Si ganas un combate en 3 turnos o menos, +20 de oro. | F88: Economía | H88: Nueva | I88: Aprobada
A89: 85 | B89: Martillo del Herrero | C89: Neutral | D89: Rara | E89: El Brujo te cobra la mitad por mejorar cartas. | F89: Mazo | H89: Nueva | I89: Aprobada
A90: 86 | B90: Lima de Hierro | C90: Neutral | D90: Rara | E90: Al obtenerla, elimina 1 carta básica de tu mazo inicial. | F90: Mazo | G90: Remover | H90: Nueva | I90: Aprobada
A91: 87 | B91: Lupa del Tasador | C91: Neutral | D91: Rara | E91: Las recompensas de combate ofrecen 1 carta más para elegir. | F91: Mazo | H91: Nueva | I91: Aprobada
A92: 88 | B92: Moneda de Dos Caras | C92: Neutral | D92: Rara | E92: Una tirada gratis de gachapón por piso. | F92: Suerte | H92: Nueva | I92: Aprobada
A93: 89 | B93: Cadena Rota | C93: Neutral | D93: Rara | E93: Las cartas de estado que te meten los enemigos se vuelven Etéreas. | F93: Mazo | H93: Nueva | I93: Aprobada | J93: Hacer una palabra clave de esto eterea
A94: 90 | B94: Pluma de Fénix | C94: Neutral | D94: Épica | E94: Si empiezas un combate con menos de la mitad de vida, te curas 8. | F94: Supervivencia | H94: Nueva | I94: Aprobada
A95: 91 | B95: Talismán del Último Aliento | C95: Neutral | D95: Épica | E95: La primera vez en cada combate que bajas del 25 % de vida, ganas 15 de escudo. | F95: Supervivencia | H95: Nueva | I95: Aprobada
A96: 92 | B96: Grillete | C96: Neutral | D96: Épica | E96: Todos los enemigos empiezan el combate con 1 de Vulnerable. | F96: Combate | H96: Nueva | I96: Aprobada
A97: 93 | B97: Baraja Mágica | C97: Neutral | D97: Épica | E97: La primera vez en cada combate que tu pila de robo se queda vacía, robas 1 carta. | F97: Mazo | G97: Robo | H97: Nueva | I97: Aprobada
A98: 94 | B98: Batería Arcana | C98: Neutral | D98: Épica | E98: Si terminas el turno con maná sin gastar, guardas 1 para el siguiente turno. | F98: Combate | G98: Maná | H98: Nueva | I98: Aprobada
A99: 95 | B99: Corazón de Piedra | C99: Neutral | D99: Épica | E99: +30 de vida máxima, pero no puedes curarte durante los combates. | F99: Supervivencia | H99: Nueva | I99: Aprobada
A100: 96 | B100: Prisma | C100: Neutral | D100: Épica | E100: Tus cartas doradas cuestan 1 menos (mínimo 1). | F100: Mazo | G100: Maná | H100: Nueva | I100: Aprobada
A101: 97 | B101: Piedra de Toque | C101: Neutral | D101: Épica | E101: Tus cartas mejoradas hacen +2 de daño y dan +2 de escudo. | F101: Mazo | H101: Nueva | I101: Aprobada
A102: 98 | B102: Bolsa sin Fondo | C102: Neutral | D102: Épica | E102: Los sobres dorados te dejan quedarte con 3 cartas en lugar de 2. | F102: Mazo | H102: Nueva | I102: Aprobada
A103: 99 | B103: Contrato Maldito | C103: Neutral | D103: Legendaria | E103: +1 de maná por turno, pero cada combate empieza con una carta Herida (Injugable) en tu pila de robo. | F103: Combate | G103: Maná | H103: Nueva | I103: Aprobada
...

Sheet Reglas de equilibrio
A1: Reglas de equilibrio — efectos muy fuertes
A3: Efecto | B3: Por qué es fuerte | C3: Límite recomendado
A4: Robar cartas | B4: Muy fuerte: más opciones cada turno y llegas antes a tus mejores cartas. | C4: Cartas: robar 1, como mucho 2. Reliquias: 1 carta, una vez por turno o por combate, o detrás de una condición difícil (cada 3 Vacíos, pila de robo vacía…).
A5: Ganar maná | B5: Muy fuerte: cada maná es una carta más jugada por turno. | C5: Cartas: +1 de maná como mucho. Reliquias: +1 con condición difícil, una vez por turno o por combate, o con una contrapartida clara (Contrato Maldito).
A6: Abaratar cartas | B6: Equivale a ganar maná. | C6: Misma regla que el maná: 1 de descuento, una vez por turno y con condición.
A7: Eliminar cartas del mazo | B7: Fuerte: un mazo más pequeño llega antes a sus combos y a las condiciones de victoria. | C7: Normalmente 1 carta. Eliminar más (Tijeras del Sastre: 3) solo en Legendaria.
A8: Excepción | B8: Con condiciones complicadas se puede dar algo más. | C8: Cuanto más difícil o arriesgada sea la condición, más puede dar el efecto.
